manage.py
drive/__init__.py
drive/asgi.py
drive/settings.py
drive/urls.py
drive/wsgi.py
sample_app/init.py
sample_app/run.py
userface/__init__.py
userface/admin.py
userface/apps.py
userface/forms.py
userface/models.py
userface/tests.py
userface/urls.py
userface/views.py
userface/media/parkingspot_uploads/Screen_Shot_2020-07-25_at_8.37.18_PM.png
userface/media/parkingspot_uploads/default_image.jpg
userface/media/parkingspot_uploads/parkingtest.jpg
userface/media/parkingspot_uploads/parkingtest_2USIkYv.jpg
userface/media/parkingspot_uploads/parkingtest_rUw35WW.jpg
userface/media/parkingspot_uploads/test_image.jpg
userface/static/css/home.css
userface/static/css/portal.css
userface/static/css/practice.css
userface/static/css/starter-template.css
userface/static/css/style.css
userface/templates/base_generic.html
userface/templates/css/bootstrap.min.css
userface/templates/css/style.css
userface/templates/css/bootstrap/_media.css
userface/templates/css/bootstrap/utilities/_stretched-link.css
userface/templates/registration/logged_out.html
userface/templates/registration/login.html
userface/templates/registration/register.html
userface/templates/userface/addspot.html
userface/templates/userface/adminportal.html
userface/templates/userface/book.html
userface/templates/userface/confirm.html
userface/templates/userface/cover.html
userface/templates/userface/index.html
userface/templates/userface/parking_spot_list.html
userface/templates/userface/register_vehicle.html
userface/templates/userface/search.html
userface/templates/userface/search_base.html
userface/templates/userface/user_vehicle_list.html
driveway-0.1.4.dist-info/LICENSE.txt
driveway-0.1.4.dist-info/METADATA
driveway-0.1.4.dist-info/WHEEL
driveway-0.1.4.dist-info/entry_points.txt
driveway-0.1.4.dist-info/top_level.txt
driveway-0.1.4.dist-info/RECORD
